ragstack_llamaindex/__init__.py
ragstack_llamaindex/colbert/__init__.py
ragstack_llamaindex/colbert/colbert_retriever.py
ragstack_llamaindex/py.typed
ragstack_ai_llamaindex-1.0.8.dist-info/METADATA
ragstack_ai_llamaindex-1.0.8.dist-info/WHEEL
ragstack_ai_llamaindex-1.0.8.dist-info/RECORD
